bc_proto_sdk-0.2.7.dist-info/METADATA
bc_proto_sdk-0.2.7.dist-info/WHEEL
bc_proto_sdk/__init__.py
bc_proto_sdk/bc_proto_sdk.cp311-win_amd64.pyd
bc_proto_sdk-0.2.7.dist-info/RECORD
