Metadata-Version: 2.4
Name: bc_proto_sdk
Version: 0.2.7
Summary: BrainCo FW proto message SDK
Author: BrainCo
License: 	
Project-URL: Source Code, https://github.com/BrainCoTech/bc_proto_sdk
